{
  "auth": "zef:raku-community-modules",
  "authors": [
    "Karl Rune Nilsen"
  ],
  "build-depends": [
  ],
  "depends": [
  ],
  "description": "Convert a Supply of bytes to a Supply of unicode characters",
  "license": "Artistic-2.0",
  "name": "Unicode::UTF8-Parser",
  "perl": "v6.0.0",
  "provides": {
    "Unicode::UTF8-Parser": "lib/Unicode/UTF8-Parser.rakumod"
  },
  "resources": [
  ],
  "source-url": "https://github.com/lizmat/Unicode-UTF8-parser.git",
  "tags": [
  ],
  "test-depends": [
  ],
  "version": "0.2"
}
